{
  "checksums": [
    {
      "id": "github_release/github.com/golangci/golangci-lint/v1.50.1/golangci-lint-1.50.1-darwin-amd64.tar.gz",
      "checksum": "0f615fb8c364f6e4a213f2ed2ff7aa1fc2b208addf29511e89c03534067bbf57",
      "algorithm": "sha256"
    },
    {
      "id": "github_release/github.com/golangci/golangci-lint/v1.50.1/golangci-lint-1.50.1-darwin-arm64.tar.gz",
      "checksum": "3ca9753d7804b34f9165427fbe339dbea69bd80be8a10e3f02c6037393b2e1c4",
      "algorithm": "sha256"
    },
    {
      "id": "github_release/github.com/golangci/golangci-lint/v1.50.1/golangci-lint-1.50.1-linux-amd64.tar.gz",
      "checksum": "4ba1dc9dbdf05b7bdc6f0e04bdfe6f63aa70576f51817be1b2540bbce017b69a",
      "algorithm": "sha256"
    },
    {
      "id": "github_release/github.com/golangci/golangci-lint/v1.50.1/golangci-lint-1.50.1-linux-arm64.tar.gz",
      "checksum": "3ea0a6d5946340f6831646e2c67a317dd9b35bdc4e09b2df953a86f09ba05d74",
      "algorithm": "sha256"
    },
    {
      "id": "github_release/github.com/golangci/golangci-lint/v1.50.1/golangci-lint-1.50.1-windows-amd64.zip",
      "checksum": "8c2da214884db02fb7f3d929672c515ae3b9d10defad4dd661c4ab365a316d68",
      "algorithm": "sha256"
    },
    {
      "id": "github_release/github.com/golangci/golangci-lint/v1.50.1/golangci-lint-1.50.1-windows-arm64.zip",
      "checksum": "7fd52d1da270fa8448c975d2500b6ef2d19db143b6cfc205de16612d6f4effa9",
      "algorithm": "sha256"
    },
    {
      "id": "github_release/github.com/goreleaser/goreleaser/v1.15.1/goreleaser_Darwin_all.tar.gz",
      "checksum": "67283D382BA746E6235A458FF47CD2633960800E107DFFDA5E72BB449082DBDF",
      "algorithm": "sha256"
    },
    {
      "id": "github_release/github.com/goreleaser/goreleaser/v1.15.1/goreleaser_Linux_arm64.tar.gz",
      "checksum": "A3EEC35B21811C36E329FFDA0EB02F5D10B10550D1539B5F02010A393FB0F86B",
      "algorithm": "sha256"
    },
    {
      "id": "github_release/github.com/goreleaser/goreleaser/v1.15.1/goreleaser_Linux_x86_64.tar.gz",
      "checksum": "3F5D861F43DCEFCF570B6E6269565ABF4BE803D54B7157E234DC7AA2C311666F",
      "algorithm": "sha256"
    },
    {
      "id": "github_release/github.com/goreleaser/goreleaser/v1.15.1/goreleaser_Windows_arm64.zip",
      "checksum": "D02EE17784E30B19C107B33383CB1B7916D5F9A5891D0447F71E0A251F9DA952",
      "algorithm": "sha256"
    },
    {
      "id": "github_release/github.com/goreleaser/goreleaser/v1.15.1/goreleaser_Windows_x86_64.zip",
      "checksum": "3CD4F807FF88ECE9968C3138F6238623D0C0C8F89688EBDE4F1698C9D517491F",
      "algorithm": "sha256"
    },
    {
      "id": "github_release/github.com/int128/ghcp/v1.13.2/ghcp_darwin_amd64.zip",
      "checksum": "8221f411ac4f2465b7cfd31efb6da4568e5fd20bad9f66ac312b23afa4520fdd",
      "algorithm": "sha256"
    },
    {
      "id": "github_release/github.com/int128/ghcp/v1.13.2/ghcp_linux_amd64.zip",
      "checksum": "6b9d9c9a7b834237b6579353477df3bb3730c11788170ad2a9e5d1230abc6216",
      "algorithm": "sha256"
    },
    {
      "id": "github_release/github.com/int128/ghcp/v1.13.2/ghcp_windows_amd64.zip",
      "checksum": "2297d27978c61272184589c3c521514291e6258c3c87ebcb16fb61b32663414e",
      "algorithm": "sha256"
    },
    {
      "id": "github_release/github.com/reviewdog/reviewdog/v0.14.1/reviewdog_0.14.1_Darwin_arm64.tar.gz",
      "checksum": "b8e79b3ae4168914f9f7ed7253d74f239a27789bcaf4af02246044000f18c532",
      "algorithm": "sha256"
    },
    {
      "id": "github_release/github.com/reviewdog/reviewdog/v0.14.1/reviewdog_0.14.1_Darwin_x86_64.tar.gz",
      "checksum": "634ef4b420916f9bb91a11ed4927bc378bd37462958998afa6c0551edc1b67c9",
      "algorithm": "sha256"
    },
    {
      "id": "github_release/github.com/reviewdog/reviewdog/v0.14.1/reviewdog_0.14.1_Linux_arm64.tar.gz",
      "checksum": "d387556ef1d291a360a3d2053a6de5ad856dd6c362dd0ac5793415b0c2c0aeb8",
      "algorithm": "sha256"
    },
    {
      "id": "github_release/github.com/reviewdog/reviewdog/v0.14.1/reviewdog_0.14.1_Linux_x86_64.tar.gz",
      "checksum": "bf0ada422e13a94aafb26bcd8ade3ae6d98e6a3db4a9c1cb17686ee64e021314",
      "algorithm": "sha256"
    },
    {
      "id": "github_release/github.com/reviewdog/reviewdog/v0.14.1/reviewdog_0.14.1_Windows_arm64.tar.gz",
      "checksum": "2b92ccebaa516a7a618f92e6c360855b0c661d905cbdd758ea957f3a46f9103d",
      "algorithm": "sha256"
    },
    {
      "id": "github_release/github.com/reviewdog/reviewdog/v0.14.1/reviewdog_0.14.1_Windows_x86_64.tar.gz",
      "checksum": "d6009abe6a5777962118fd227a2a9e6bafc1e15368af76d54eae88cf8631e1ad",
      "algorithm": "sha256"
    },
    {
      "id": "github_release/github.com/rhysd/actionlint/v1.6.23/actionlint_1.6.23_darwin_amd64.tar.gz",
      "checksum": "54f000f84d3fe85012a8726cd731c4101202c787963c9f8b40d15086b003d48e",
      "algorithm": "sha256"
    },
    {
      "id": "github_release/github.com/rhysd/actionlint/v1.6.23/actionlint_1.6.23_darwin_arm64.tar.gz",
      "checksum": "ddd0263968f7f024e49bd8721cd2b3d27c7a4d77081b81a4b376d5053ea25cdc",
      "algorithm": "sha256"
    },
    {
      "id": "github_release/github.com/rhysd/actionlint/v1.6.23/actionlint_1.6.23_linux_amd64.tar.gz",
      "checksum": "b39e7cd53f4a317aecfb09edcebcc058df9ebef967866e11aa7f0df27339af3b",
      "algorithm": "sha256"
    },
    {
      "id": "github_release/github.com/rhysd/actionlint/v1.6.23/actionlint_1.6.23_linux_arm64.tar.gz",
      "checksum": "a36ba721621e861e900d36457836bfd6a29d6e10d9edebe547544a0e3dbf4348",
      "algorithm": "sha256"
    },
    {
      "id": "github_release/github.com/rhysd/actionlint/v1.6.23/actionlint_1.6.23_windows_amd64.zip",
      "checksum": "ed8c80ec82c6995efd1f957cbf4c251fe208a3546e4afd8637d4b3709dbd8cc1",
      "algorithm": "sha256"
    },
    {
      "id": "github_release/github.com/rhysd/actionlint/v1.6.23/actionlint_1.6.23_windows_arm64.zip",
      "checksum": "4ffb7d53776e5d90412cf53ed99f944f17f5193173b14b84adaaaa504d5731fa",
      "algorithm": "sha256"
    },
    {
      "id": "github_release/github.com/sigstore/cosign/v1.13.1/cosign-darwin-amd64",
      "checksum": "1d164b8b1fcfef1e1870d809edbb9862afd5995cab63687a440b84cca5680ecf",
      "algorithm": "sha256"
    },
    {
      "id": "github_release/github.com/sigstore/cosign/v1.13.1/cosign-darwin-arm64",
      "checksum": "02bef878916be048fd7dcf742105639f53706a59b5b03f4e4eaccc01d05bc7ab",
      "algorithm": "sha256"
    },
    {
      "id": "github_release/github.com/sigstore/cosign/v1.13.1/cosign-linux-amd64",
      "checksum": "a50651a67b42714d6f1a66eb6773bf214dacae321f04323c0885f6a433051f95",
      "algorithm": "sha256"
    },
    {
      "id": "github_release/github.com/sigstore/cosign/v1.13.1/cosign-linux-arm64",
      "checksum": "a7a79a52c7747e2c21554cad4600e6c7130c0429017dd258f9c558d957fa9090",
      "algorithm": "sha256"
    },
    {
      "id": "github_release/github.com/sigstore/cosign/v1.13.1/cosign-windows-amd64.exe",
      "checksum": "78a2774b68b995cc698944f6c235b1c93dcb6d57593a58a565ee7a56d64e4b85",
      "algorithm": "sha256"
    },
    {
      "id": "github_release/github.com/suzuki-shunsuke/cmdx/v1.6.1/cmdx_darwin_amd64.tar.gz",
      "checksum": "7f777d9c1e2574294ea0d7c04cabadf3735b91f630f8fb1f74b2c74aec27a521",
      "algorithm": "sha256"
    },
    {
      "id": "github_release/github.com/suzuki-shunsuke/cmdx/v1.6.1/cmdx_linux_amd64.tar.gz",
      "checksum": "38cf6710909e69c732df8cacac95c53989642736b197f9c40eb71484768f25c8",
      "algorithm": "sha256"
    },
    {
      "id": "github_release/github.com/suzuki-shunsuke/cmdx/v1.6.1/cmdx_windows_amd64.tar.gz",
      "checksum": "3a036b06c16b4f3416cd46e96217af1c830378a6e8d74daf5d3596abb886044a",
      "algorithm": "sha256"
    },
    {
      "id": "github_release/github.com/suzuki-shunsuke/ghalint/v0.2.2/ghalint_0.2.2_darwin_amd64.tar.gz",
      "checksum": "2F520D13DB10EF8ABD3942DEC2CEA1792B0A7289F7466219B252169AA8124177",
      "algorithm": "sha256"
    },
    {
      "id": "github_release/github.com/suzuki-shunsuke/ghalint/v0.2.2/ghalint_0.2.2_darwin_arm64.tar.gz",
      "checksum": "3BF497D0C62B70DBC4379418D7009689937D9B5499A59E2B0B8D29A4941B81A7",
      "algorithm": "sha256"
    },
    {
      "id": "github_release/github.com/suzuki-shunsuke/ghalint/v0.2.2/ghalint_0.2.2_linux_amd64.tar.gz",
      "checksum": "A74B5A64A18BCA0077593D21E9DADBD01657D05EE6DB95467A285B1E4A904CA5",
      "algorithm": "sha256"
    },
    {
      "id": "github_release/github.com/suzuki-shunsuke/ghalint/v0.2.2/ghalint_0.2.2_linux_arm64.tar.gz",
      "checksum": "6A68353872D10DAD8CDC7F4F9592D887F127D064511BA89FF89FAFC1DDCB7492",
      "algorithm": "sha256"
    },
    {
      "id": "github_release/github.com/suzuki-shunsuke/ghalint/v0.2.2/ghalint_0.2.2_windows_amd64.tar.gz",
      "checksum": "D83BAFC44A5F218D42533140EBE924EFF483357718CE784C6E19010C553C0A0A",
      "algorithm": "sha256"
    },
    {
      "id": "github_release/github.com/suzuki-shunsuke/ghalint/v0.2.2/ghalint_0.2.2_windows_arm64.tar.gz",
      "checksum": "3B733BC72D27C83E73C4F8D7691BF7781DCC5E3BF2378C441A70AA44202D83F2",
      "algorithm": "sha256"
    },
    {
      "id": "registries/github_content/github.com/aquaproj/aqua-registry/v3.127.0/registry.yaml",
      "checksum": "603942e90f42411891411460a1ff5ceac0e9ae9233cc828b7cab5d8bedd76d90bbe5476e6744c50de6827869da2641562990fe649dd5f872cb98397b2e2c30e6",
      "algorithm": "sha512"
    }
  ]
}
